llm_chat/__init__.py
llm_chat/chat.py
llm_chat/cli.py
llm_chat/clients.py
llm_chat/config.py
llm_chat/setup.py
llm_chat/tools.py
llm_chat/utils.py
llm_chat_cli-0.0.7.dist-info/METADATA
llm_chat_cli-0.0.7.dist-info/WHEEL
llm_chat_cli-0.0.7.dist-info/entry_points.txt
llm_chat_cli-0.0.7.dist-info/top_level.txt
llm_chat_cli-0.0.7.dist-info/RECORD
